pyfms/__init__.py
pyfms/core.py
pyfms/errors.py
pyfms/models.py
pyfms/optimizers.py
pyfms/regularizers.py
pyfms/transformers.py
pyfms/utils.py
pyfms/version.txt
pyfms-0.4.0.dist-info/LICENSE
pyfms-0.4.0.dist-info/METADATA
pyfms-0.4.0.dist-info/WHEEL
pyfms-0.4.0.dist-info/top_level.txt
pyfms-0.4.0.dist-info/RECORD
