Metadata-Version: 2.1
Name: pyfms
Version: 0.4.0
Summary: A Theano-based Python implementation of Factorization Machines
Home-page: https://github.com/dstein64/pyfms
Author: Daniel Steinberg
Author-email: ds@dannyadam.com
License: MIT
Keywords: factorization-machines,machine-learning
Platform: UNKNOWN
Classifier: Development Status :: 4 - Beta
Classifier: Intended Audience :: Developers
Classifier: Intended Audience :: Science/Research
Classifier: Topic :: Scientific/Engineering
Classifier: Topic :: Scientific/Engineering :: Artificial Intelligence
Classifier: Topic :: Scientific/Engineering :: Information Analysis
Classifier: License :: OSI Approved :: MIT License
Classifier: Operating System :: Unix
Classifier: Operating System :: POSIX :: Linux
Classifier: Operating System :: MacOS
Classifier: Operating System :: Microsoft :: Windows
Classifier: Programming Language :: Python :: 2.7
Classifier: Programming Language :: Python :: 3
Classifier: Programming Language :: Python :: 3.6
Requires-Dist: numpy
Requires-Dist: theano (>=0.8.0)
Provides-Extra: dev
Requires-Dist: scikit-learn ; extra == 'dev'
